fr24/__init__.py
fr24/__main__.py
fr24/authentication.py
fr24/cache.py
fr24/cli.py
fr24/configuration.py
fr24/grpc.py
fr24/json.py
fr24/py.typed
fr24/service.py
fr24/utils.py
fr24/proto/CHANGELOG.md
fr24/proto/README.md
fr24/proto/__init__.py
fr24/proto/_common.proto
fr24/proto/_common_pb2.py
fr24/proto/_common_pb2.pyi
fr24/proto/_fetch_search_index.proto
fr24/proto/_fetch_search_index_pb2.py
fr24/proto/_fetch_search_index_pb2.pyi
fr24/proto/_flight_details.proto
fr24/proto/_flight_details_pb2.py
fr24/proto/_flight_details_pb2.pyi
fr24/proto/_follow_flight.proto
fr24/proto/_follow_flight_pb2.py
fr24/proto/_follow_flight_pb2.pyi
fr24/proto/_health.proto
fr24/proto/_health_pb2.py
fr24/proto/_health_pb2.pyi
fr24/proto/_historic_trail.proto
fr24/proto/_historic_trail_pb2.py
fr24/proto/_historic_trail_pb2.pyi
fr24/proto/_live_feed.proto
fr24/proto/_live_feed_pb2.py
fr24/proto/_live_feed_pb2.pyi
fr24/proto/_live_flight_status.proto
fr24/proto/_live_flight_status_pb2.py
fr24/proto/_live_flight_status_pb2.pyi
fr24/proto/_live_trail.proto
fr24/proto/_live_trail_pb2.py
fr24/proto/_live_trail_pb2.pyi
fr24/proto/_nearest_flights.proto
fr24/proto/_nearest_flights_pb2.py
fr24/proto/_nearest_flights_pb2.pyi
fr24/proto/_playback_flight.proto
fr24/proto/_playback_flight_pb2.py
fr24/proto/_playback_flight_pb2.pyi
fr24/proto/_top_flights.proto
fr24/proto/_top_flights_pb2.py
fr24/proto/_top_flights_pb2.pyi
fr24/proto/headers.py
fr24/proto/v1.proto
fr24/proto/v1_pb2.py
fr24/proto/v1_pb2.pyi
fr24/static/__init__.py
fr24/static/bbox.py
fr24/tui/__init__.py
fr24/tui/formatters.py
fr24/tui/style.tcss
fr24/tui/tui.py
fr24/tui/widgets.py
fr24/types/__init__.py
fr24/types/cache.py
fr24/types/grpc.py
fr24/types/json.py
fr24/types/static.py
fr24-0.2.2.dist-info/METADATA
fr24-0.2.2.dist-info/WHEEL
fr24-0.2.2.dist-info/entry_points.txt
fr24-0.2.2.dist-info/licenses/LICENSE
fr24-0.2.2.dist-info/RECORD
