Metadata-Version: 2.4
Name: fr24
Version: 0.2.2
Summary: Parse gRPC and JSON data from flightradar24
Project-URL: Repository, https://github.com/abc8747/fr24.git
Project-URL: Documentation, https://abc8747.github.io/fr24/
Project-URL: Issues, https://github.com/abc8747/fr24/issues
Author-email: Abraham Cheung <abraham@ylcheung.com>, Xavier Olive <git@xoolive.org>
License: MIT License
License-File: LICENSE
Classifier: Development Status :: 4 - Beta
Classifier: Intended Audience :: Information Technology
Classifier: Intended Audience :: Science/Research
Classifier: License :: OSI Approved :: MIT License
Classifier: Programming Language :: Python :: 3
Classifier: Programming Language :: Python :: 3.9
Classifier: Programming Language :: Python :: 3.10
Classifier: Programming Language :: Python :: 3.11
Classifier: Programming Language :: Python :: 3.12
Classifier: Programming Language :: Python :: 3.13
Classifier: Programming Language :: Python :: 3.14
Classifier: Typing :: Typed
Requires-Python: >=3.9
Requires-Dist: httpx[http2,zstd]>=0.28.1
Requires-Dist: orjson>=3.11.0
Requires-Dist: platformdirs>=4.3.8
Requires-Dist: polars>=1.19.0
Requires-Dist: protobuf==5.28.*
Provides-Extra: cli
Requires-Dist: typer>=0.19; extra == 'cli'
Provides-Extra: rich
Requires-Dist: loguru; extra == 'rich'
Requires-Dist: rich; extra == 'rich'
Provides-Extra: tui
Requires-Dist: pandas>=2.2.3; extra == 'tui'
Requires-Dist: textual>=1.0.0; extra == 'tui'
